pytest_html_report_merger/__init__.py
pytest_html_report_merger/__main__.py
pytest_html_report_merger-0.1.3.dist-info/LICENSE
pytest_html_report_merger-0.1.3.dist-info/METADATA
pytest_html_report_merger-0.1.3.dist-info/WHEEL
pytest_html_report_merger-0.1.3.dist-info/entry_points.txt
pytest_html_report_merger-0.1.3.dist-info/RECORD
